py_dir_sync/__init__.py
py_dir_sync/filter.py
py_dir_sync/handler.py
py_dir_sync/matcher.py
py_dir_sync/pair.py
py_dir_sync/py.typed
py_dir_sync/scheduler.py
py_dir_sync/synchronizer.py
py_dir_sync/types.py
py_dir_sync/utils.py
py_dir_sync/watcher.py
py_dir_sync-0.1.0.dist-info/licenses/LICENSE.md
py_dir_sync-0.1.0.dist-info/METADATA
py_dir_sync-0.1.0.dist-info/WHEEL
py_dir_sync-0.1.0.dist-info/top_level.txt
py_dir_sync-0.1.0.dist-info/RECORD
