Metadata-Version: 2.4
Name: py_dir_sync
Version: 0.1.0
Summary: One-way directory synchronization
Author-email: Alexander Lonberg <alexlonberg@gmail.com>
License: MIT License
Project-URL: Homepage, https://github.com/AlexLonberg/py_dir_sync
Project-URL: Repository, https://github.com/AlexLonberg/py_dir_sync.git
Keywords: py_dir_sync,observer,synchronization
Requires-Python: >=3.12
License-File: LICENSE.md
Requires-Dist: watchdog<7.0.0,>=6.0.0
Dynamic: license-file
